<annotation>
	<folder>no_results</folder>
	<filename>9902609244.jpg</filename>
	<path>C:\Users\Deres\Downloads\failed_images-20221011T173952Z-001\failed_images\no_results\9902609244.jpg</path>
	<source>
		<database>Unknown</database>
	</source>
	<size>
		<width>3226</width>
		<height>3402</height>
		<depth>3</depth>
	</size>
	<segmented>0</segmented>
	<object>
		<name>noresult</name>
		<pose>Unspecified</pose>
		<truncated>0</truncated>
		<difficult>0</difficult>
		<bndbox>
			<xmin>1240</xmin>
			<ymin>230</ymin>
			<xmax>2578</xmax>
			<ymax>1116</ymax>
		</bndbox>
	</object>
</annotation>
